odoo/addons/purchase_order_uninvoiced_amount/README.rst
odoo/addons/purchase_order_uninvoiced_amount/__init__.py
odoo/addons/purchase_order_uninvoiced_amount/__manifest__.py
odoo/addons/purchase_order_uninvoiced_amount/i18n/en_US.po
odoo/addons/purchase_order_uninvoiced_amount/i18n/es.po
odoo/addons/purchase_order_uninvoiced_amount/i18n/purchase_order_uninvoiced_amount.pot
odoo/addons/purchase_order_uninvoiced_amount/models/__init__.py
odoo/addons/purchase_order_uninvoiced_amount/models/purchase_order.py
odoo/addons/purchase_order_uninvoiced_amount/readme/CONTRIBUTORS.rst
odoo/addons/purchase_order_uninvoiced_amount/readme/DESCRIPTION.rst
odoo/addons/purchase_order_uninvoiced_amount/static/description/icon.png
odoo/addons/purchase_order_uninvoiced_amount/static/description/index.html
odoo/addons/purchase_order_uninvoiced_amount/tests/__init__.py
odoo/addons/purchase_order_uninvoiced_amount/tests/test_purchase_order_uninvoiced_amount.py
odoo/addons/purchase_order_uninvoiced_amount/views/purchase_order_view.xml
odoo13_addon_purchase_order_uninvoiced_amount-13.0.2.2.0.dist-info/METADATA
odoo13_addon_purchase_order_uninvoiced_amount-13.0.2.2.0.dist-info/WHEEL
odoo13_addon_purchase_order_uninvoiced_amount-13.0.2.2.0.dist-info/top_level.txt
odoo13_addon_purchase_order_uninvoiced_amount-13.0.2.2.0.dist-info/RECORD
